pyAutoAss/Listening.py
pyAutoAss/__init__.py
pyAutoAss/pyAutoGui.py
pyAutoAss/pyAutoKeyboard.py
pyAutoAss/pyAutoMouse.py
pyAutoAss/pyautoAss.py
pyAutoAss/pyclipboard.py
pyAutoAss/dependent/DataType.py
pyAutoAss/utils/MCODE.py
pyAutoAss/utils/Utils.py
pyAutoAss/utils/VKCODE.py
pyautoass-1.0.6.3.dist-info/licenses/LICENSE
pyautoass-1.0.6.3.dist-info/METADATA
pyautoass-1.0.6.3.dist-info/WHEEL
pyautoass-1.0.6.3.dist-info/top_level.txt
pyautoass-1.0.6.3.dist-info/zip-safe
pyautoass-1.0.6.3.dist-info/RECORD
