Metadata-Version: 2.4
Name: pyautoass
Version: 1.0.6.3
Summary: 基于键鼠、图片定位的自动化gui工作套件。
Author: awise
Requires-Python: >=3
License-File: LICENSE
Requires-Dist: pyautogui
Requires-Dist: opencv-python
Requires-Dist: pywin32
Dynamic: author
Dynamic: description
Dynamic: license-file
Dynamic: requires-dist
Dynamic: requires-python
Dynamic: summary
